bagbag/Base64/__init__.py
bagbag/Base64/src.py
bagbag/Cmd/__init__.py
bagbag/Cmd/src.py
bagbag/Cryptoo/__init__.py
bagbag/Cryptoo/src.py
bagbag/File/__init__.py
bagbag/File/src.py
bagbag/Funcs/ChromeExtension_src.py
bagbag/Funcs/CountryNameConvert_src.py
bagbag/Funcs/CutSentenceStopWords_src.py
bagbag/Funcs/CutSentence_src.py
bagbag/Funcs/FakeIdentity_src.py
bagbag/Funcs/FileType_src.py
bagbag/Funcs/Format/__init__.py
bagbag/Funcs/Format/src.py
bagbag/Funcs/IP_src.py
bagbag/Funcs/MarkCoordinatesOnMap_src.py
bagbag/Funcs/Markdown_src.py
bagbag/Funcs/Ping_src.py
bagbag/Funcs/ResizeImage_src.py
bagbag/Funcs/UUID_src.py
bagbag/Funcs/VersionCompare_src.py
bagbag/Funcs/Wget_src.py
bagbag/Funcs/Whois_src.py
bagbag/Funcs/__init__.py
bagbag/Funcs/whois/__init__.py
bagbag/Funcs/whois/data/public_suffix_list.dat
bagbag/Funcs/whois/parser.py
bagbag/Funcs/whois/time_zones.py
bagbag/Funcs/whois/whois.py
bagbag/Hash/__init__.py
bagbag/Hash/src.py
bagbag/Http/__init__.py
bagbag/Http/src.py
bagbag/Json/__init__.py
bagbag/Json/src.py
bagbag/Lg.py
bagbag/Math/__init__.py
bagbag/Math/src.py
bagbag/Os/Path/__init__.py
bagbag/Os/Path/src.py
bagbag/Os/__init__.py
bagbag/Os/src.py
bagbag/Process/__init__.py
bagbag/Process/src.py
bagbag/Python/__init__.py
bagbag/Python/src.py
bagbag/Random/__init__.py
bagbag/Random/src.py
bagbag/Socket/TCP/__init__.py
bagbag/Socket/TCP/src.py
bagbag/Socket/UDP/__init__.py
bagbag/Socket/UDP/src.py
bagbag/Socket/__init__.py
bagbag/String/__init__.py
bagbag/String/src.py
bagbag/String/stopwords.txt
bagbag/String/tlds.txt
bagbag/String/vars.py
bagbag/Thread/__init__.py
bagbag/Thread/src.py
bagbag/Time/__init__.py
bagbag/Time/src.py
bagbag/Tools/Argparser_src.py
bagbag/Tools/BlockChain/Binance/CoinsPrice_src.py
bagbag/Tools/BlockChain/Binance/OfficialAccountVertify/__init__.py
bagbag/Tools/BlockChain/Binance/OfficialAccountVertify/src.py
bagbag/Tools/BlockChain/Binance/__init__.py
bagbag/Tools/BlockChain/CoinMarketCap/__init__.py
bagbag-0.75.43.dist-info/LICENSE
bagbag-0.75.43.dist-info/METADATA
bagbag-0.75.43.dist-info/WHEEL
bagbag-0.75.43.dist-info/RECORD
