Metadata-Version: 2.3
Name: bagbag
Version: 0.75.43
Summary: An all in one python library
License: MIT
Keywords: base,library
Author: Darren
Requires-Python: >=3.9
Classifier: License :: OSI Approved :: MIT License
Classifier: Programming Language :: Python :: 3
Classifier: Programming Language :: Python :: 3.9
Classifier: Programming Language :: Python :: 3.10
Classifier: Programming Language :: Python :: 3.11
Classifier: Programming Language :: Python :: 3.12
Classifier: Programming Language :: Python :: 3.13
Requires-Dist: Faker (>=0.8)
Requires-Dist: Flask (>=2.1.3)
Requires-Dist: Js2Py (>=0.74)
Requires-Dist: Levenshtein (>=0.23.0)
Requires-Dist: OpenCC (>=0.2)
Requires-Dist: Pillow (>=9.2.0)
Requires-Dist: PyGithub (>=1.57)
Requires-Dist: PyMySQL (>=1.0.2)
Requires-Dist: Pygments (>=2.2)
Requires-Dist: backpack (>=0.1)
Requires-Dist: bcrypt (==4.0.1)
Requires-Dist: beautifulsoup4 (>=4.11.1)
Requires-Dist: blinker (>=1.4)
Requires-Dist: cachetools (>=4.2.4)
Requires-Dist: cleo (>=0.6)
Requires-Dist: demjson3 (>=3.0.6)
Requires-Dist: feedparser (>=6.0.10)
Requires-Dist: future (>=0.18.2)
Requires-Dist: hachoir (>=3.2.0)
Requires-Dist: hanzidentifier (>=1.2.0)
Requires-Dist: html-to-json (>=2.0.0)
Requires-Dist: html5lib (>=1.1)
Requires-Dist: inflection (>=0.3)
Requires-Dist: ipdb (>=0.13.9)
Requires-Dist: ipwhois (>=1.2.0)
Requires-Dist: jieba (>=0.42.1)
Requires-Dist: json_repair (>=0.46.0)
Requires-Dist: kafka-python (>=2.0.2)
Requires-Dist: langid (>=1.1.6)
Requires-Dist: lazy-imports (==0.3.1)
Requires-Dist: lazy-object-proxy (>=1.2)
Requires-Dist: listparser (>=0.19)
Requires-Dist: loguru (>=0.6.0)
Requires-Dist: lxml (>=4.9.1)
Requires-Dist: lz4 (>=4.3.3)
Requires-Dist: markdown2 (>=2.4.9)
Requires-Dist: markdownify (>=0.11.6)
Requires-Dist: matplotlib (>=3.9.0)
Requires-Dist: mitmproxy (>=10.3.1)
Requires-Dist: msgpack (>=1.0.4)
Requires-Dist: nltk (>=3.8.1)
Requires-Dist: nslookup (>=1.6.1)
Requires-Dist: openai (>=1.6.1)
Requires-Dist: opencv-python (>=4.6.0.66)
Requires-Dist: openpyxl (>=3.0.10)
Requires-Dist: packaging (>=20.9)
Requires-Dist: paramiko (>=2.11.0)
Requires-Dist: pendulum (>=1.4)
Requires-Dist: pillow (>=10.3.0)
Requires-Dist: prometheus-client (>=0.14.1)
Requires-Dist: psutil (>=5.9.1)
Requires-Dist: pyTelegramBotAPI (>=4.13.0)
Requires-Dist: pyaml (>=16.12)
Requires-Dist: pybase64 (>=1.2.3)
Requires-Dist: pycryptodome (>=3.15.0)
Requires-Dist: pygtrans (>=1.4.0)
Requires-Dist: pymongo (>=4.8.0)
Requires-Dist: pypinyin (>=0.47.1)
Requires-Dist: python-dateutil (>=2.8.2)
Requires-Dist: python-magic (>=0.4.27)
Requires-Dist: pythonping (>=1.1.3)
Requires-Dist: pytz (>=2022.1)
Requires-Dist: pyyaml (>=5.1)
Requires-Dist: random-user-agent (>=1.0.1)
Requires-Dist: redis (>=4.3.4)
Requires-Dist: requests (>=2.28.1)
Requires-Dist: requests-toolbelt (>=0.9.1)
Requires-Dist: schedule (>=1.1.0)
Requires-Dist: scikit-learn (>=1.3.0)
Requires-Dist: selenium (>=4.3.0)
Requires-Dist: selenium-wire (>=5.1.0)
Requires-Dist: service-identity (>=24.1.0)
Requires-Dist: shortuuid (>=1.0.9)
Requires-Dist: simplejson (>=3.10)
Requires-Dist: six (>=1.10)
Requires-Dist: telethon (>=1.24.0)
Requires-Dist: tiktoken (>=0.9.0)
Requires-Dist: tld (>=0.13)
Requires-Dist: tldextract (>=5.1.2)
Requires-Dist: tqdm (>=4.64.0)
Requires-Dist: tronpy (>=0.2.6)
Requires-Dist: tweepy (>=4.12.1)
Requires-Dist: vaderSentiment (>=3.3.2)
Requires-Dist: validators (>=0.20.0)
Requires-Dist: vncdotool (>=1.2.0)
Requires-Dist: windows-curses (>=2.3.0) ; sys_platform == "win32"
Requires-Dist: wrapt (>=1.10)
Project-URL: Repository, https://github.com/darren2046/bagbag
